newsletter/__init__.py
newsletter/admin.py
newsletter/admin_forms.py
newsletter/admin_utils.py
newsletter/converters.py
newsletter/fields.py
newsletter/forms.py
newsletter/models.py
newsletter/settings.py
newsletter/urls.py
newsletter/utils.py
newsletter/validators.py
newsletter/views.py
newsletter/__pycache__/__init__.cpython-312.pyc
newsletter/addressimport/__init__.py
newsletter/addressimport/parsers.py
newsletter/generator/__init__.py
newsletter/generator/admin.py
newsletter/generator/forms.py
newsletter/generator/models.py
newsletter/generator/utils.py
newsletter/generator/views.py
newsletter/jobs/__init__.py
newsletter/jobs/daily/__init__.py
newsletter/jobs/hourly/__init__.py
newsletter/jobs/hourly/submit.py
newsletter/jobs/monthly/__init__.py
newsletter/jobs/weekly/__init__.py
newsletter/locale/ar/LC_MESSAGES/django.mo
newsletter/locale/ar/LC_MESSAGES/django.po
newsletter/locale/ar/LC_MESSAGES/djangojs.mo
newsletter/locale/ar/LC_MESSAGES/djangojs.po
newsletter/locale/cs_CZ/LC_MESSAGES/django.mo
newsletter/locale/cs_CZ/LC_MESSAGES/django.po
newsletter/locale/cs_CZ/LC_MESSAGES/djangojs.mo
newsletter/locale/cs_CZ/LC_MESSAGES/djangojs.po
newsletter/locale/de/LC_MESSAGES/django.mo
newsletter/locale/de/LC_MESSAGES/django.po
newsletter/locale/de/LC_MESSAGES/djangojs.mo
newsletter/locale/de/LC_MESSAGES/djangojs.po
newsletter/locale/el_GR/LC_MESSAGES/django.mo
newsletter/locale/el_GR/LC_MESSAGES/django.po
newsletter/locale/el_GR/LC_MESSAGES/djangojs.mo
newsletter/locale/el_GR/LC_MESSAGES/djangojs.po
newsletter/locale/en/LC_MESSAGES/django.mo
newsletter/locale/en/LC_MESSAGES/django.po
newsletter/locale/en/LC_MESSAGES/djangojs.mo
newsletter/locale/en/LC_MESSAGES/djangojs.po
newsletter/locale/es/LC_MESSAGES/django.mo
newsletter/locale/es/LC_MESSAGES/django.po
newsletter/locale/es/LC_MESSAGES/djangojs.mo
newsletter/locale/es/LC_MESSAGES/djangojs.po
newsletter/locale/fa/LC_MESSAGES/django.mo
newsletter/locale/fa/LC_MESSAGES/django.po
django_oscar_newsletter-0.10.1.dist-info/AUTHORS.rst
django_oscar_newsletter-0.10.1.dist-info/LICENSE.txt
django_oscar_newsletter-0.10.1.dist-info/METADATA
django_oscar_newsletter-0.10.1.dist-info/WHEEL
django_oscar_newsletter-0.10.1.dist-info/top_level.txt
django_oscar_newsletter-0.10.1.dist-info/RECORD
